ainb/__init__.py
ainb/__main__.py
ainb/action.py
ainb/ainb.py
ainb/attachment.py
ainb/blackboard.py
ainb/command.py
ainb/common.py
ainb/enum_resolve.py
ainb/module.py
ainb/node.py
ainb/param.py
ainb/param_common.py
ainb/property.py
ainb/py.typed
ainb/replacement.py
ainb/state.py
ainb/transition.py
ainb/unknown.py
ainb/utils.py
ainb/write_context.py
ainb/data/__init__.py
ainb/data/nss.json
ainb/data/s3.json
ainb/expression/__init__.py
ainb/expression/common.py
ainb/expression/disassemble.py
ainb/expression/expression.py
ainb/expression/instruction.py
ainb/expression/module.py
ainb/expression/parser.py
ainb/expression/write_context.py
ainb/graph/__init__.py
ainb/graph/__main__.py
ainb/graph/graph.py
ainb-0.2.8.dist-info/licenses/LICENSE
ainb-0.2.8.dist-info/METADATA
ainb-0.2.8.dist-info/WHEEL
ainb-0.2.8.dist-info/entry_points.txt
ainb-0.2.8.dist-info/top_level.txt
ainb-0.2.8.dist-info/RECORD
