Metadata-Version: 2.4
Name: ainb
Version: 0.2.8
Project-URL: Homepage, https://github.com/dt-12345/AINB
Classifier: Programming Language :: Python :: 3
Classifier: Operating System :: OS Independent
Requires-Python: >=3.10
License-File: LICENSE
Requires-Dist: mmh3
Provides-Extra: graph
Requires-Dist: graphviz; extra == "graph"
Dynamic: license-file
